github_actions_deploy/__init__.py
github_actions_deploy/cli.py
github_actions_deploy/config.py
github_actions_deploy/deployer.py
github_actions_deploy/github_comments.py
github_actions_deploy/vpc_sc.py
github_actions_deploy-0.1.0.dist-info/licenses/LICENSE
github_actions_deploy-0.1.0.dist-info/METADATA
github_actions_deploy-0.1.0.dist-info/WHEEL
github_actions_deploy-0.1.0.dist-info/entry_points.txt
github_actions_deploy-0.1.0.dist-info/top_level.txt
github_actions_deploy-0.1.0.dist-info/RECORD
