Metadata-Version: 2.4
Name: github-actions-deploy
Version: 0.1.0
Summary: GitHub Actions deployment automation with VPC-SC support and PR commenting
Author-email: Jeffrey Lee-Chan <jleechan2015@gmail.com>
License: MIT
Project-URL: Homepage, https://github.com/jleechanorg/ai_universe
Project-URL: Repository, https://github.com/jleechanorg/ai_universe
Project-URL: Documentation, https://github.com/jleechanorg/ai_universe/tree/main/packages/github-actions-deploy
Project-URL: Bug Tracker, https://github.com/jleechanorg/ai_universe/issues
Keywords: github-actions,deployment,gcp,cloud-run,vpc-sc,cicd
Classifier: Development Status :: 4 - Beta
Classifier: Intended Audience :: Developers
Classifier: License :: OSI Approved :: MIT License
Classifier: Operating System :: OS Independent
Classifier: Programming Language :: Python :: 3
Classifier: Programming Language :: Python :: 3.8
Classifier: Programming Language :: Python :: 3.9
Classifier: Programming Language :: Python :: 3.10
Classifier: Programming Language :: Python :: 3.11
Classifier: Programming Language :: Python :: 3.12
Classifier: Topic :: Software Development :: Build Tools
Classifier: Topic :: System :: Systems Administration
Requires-Python: >=3.8
License-File: LICENSE
Requires-Dist: google-cloud-run>=0.10.0
Requires-Dist: google-cloud-build>=3.13.0
Requires-Dist: google-auth>=2.17.0
Requires-Dist: PyGithub>=1.58.0
Requires-Dist: pydantic>=2.0.0
Requires-Dist: click>=8.0.0
Requires-Dist: rich>=12.0.0
Requires-Dist: pyyaml>=6.0
Provides-Extra: dev
Requires-Dist: pytest>=7.0.0; extra == "dev"
Requires-Dist: pytest-asyncio>=0.21.0; extra == "dev"
Requires-Dist: black>=23.0.0; extra == "dev"
Requires-Dist: isort>=5.12.0; extra == "dev"
Requires-Dist: mypy>=1.0.0; extra == "dev"
Requires-Dist: pre-commit>=3.0.0; extra == "dev"
Dynamic: license-file
